LICENSE
MANIFEST.in
README.md
build_upload.md
pyproject.toml
requirements.txt
setup.cfg
setup.py
src/cdp_socket/__init__.py
src/cdp_socket/exceptions.py
src/cdp_socket/socket.py
src/cdp_socket.egg-info/PKG-INFO
src/cdp_socket.egg-info/SOURCES.txt
src/cdp_socket.egg-info/dependency_links.txt
src/cdp_socket.egg-info/requires.txt
src/cdp_socket.egg-info/top_level.txt
src/cdp_socket/files/__init__.py
src/cdp_socket/scripts/__init__.py
src/cdp_socket/scripts/abstract.py
src/cdp_socket/utils/__init__.py
src/cdp_socket/utils/conn.py
src/cdp_socket/utils/utils.py
tests/check_event.py
tests/test_socket.py