Metadata-Version: 2.1
Name: cdp-socket
Version: 1.2.4
Summary: socket for handling chrome-developer-protocol connections
Home-page: https://github.com/kaliiiiiiiiii/CDP-Socket
Author: Aurin Aegerter
Author-email: aurinliun@gmx.ch
License: MIT
Project-URL: Documentation, https://github.com/kaliiiiiiiiii/CDP-Socket
Project-URL: Bug Reports, https://github.com/kaliiiiiiiiii/CDP-Socket/issues
Project-URL: Source Code, https://github.com/kaliiiiiiiiii/CDP-Socket
Keywords: Chromium,socket,webautomation
Classifier: Development Status :: 2 - Pre-Alpha
Classifier: Intended Audience :: Developers
Classifier: Programming Language :: Python :: 3
Classifier: Programming Language :: Python :: 3.7
Classifier: Programming Language :: Python :: 3.8
Classifier: Programming Language :: Python :: 3.9
Classifier: Programming Language :: Python :: 3.10
Classifier: Programming Language :: Python :: 3.11
Classifier: License :: Free for non-commercial use
Classifier: Natural Language :: English
Classifier: Operating System :: OS Independent
Classifier: Topic :: Communications
Classifier: Topic :: Internet :: WWW/HTTP :: Browsers
Requires-Python: >=3.7
Requires-Dist: aiohttp
Requires-Dist: websockets
Requires-Dist: orjson
Provides-Extra: dev
Requires-Dist: check-manifest; extra == "dev"
